chemicalspace/__init__.py
chemicalspace/space.py
chemicalspace/utils.py
chemicalspace/layers/__init__.py
chemicalspace/layers/acquisition.py
chemicalspace/layers/base.py
chemicalspace/layers/clustering.py
chemicalspace/layers/diversity.py
chemicalspace/layers/neighbors.py
chemicalspace/layers/projection.py
chemicalspace-0.1.1.dist-info/LICENSE.md
chemicalspace-0.1.1.dist-info/METADATA
chemicalspace-0.1.1.dist-info/WHEEL
chemicalspace-0.1.1.dist-info/top_level.txt
chemicalspace-0.1.1.dist-info/RECORD
