Metadata-Version: 2.1
Name: chemicalspace
Version: 0.1.1
Summary: An Object-oriented Representation for Chemical Spaces
Author-email: Giulio Mattedi <giulio.mattedi@gmail.com>
Maintainer-email: Giulio Mattedi <giulio.mattedi@gmail.com>
License: MIT License
Project-URL: Homepage, https://github.com/gmattedi/chemicalspace
Project-URL: Issues, https://github.com/gmattedi/chemicalspace/issues
Keywords: chemistry,cheminformatics,rdkit,machine learning,ml
Classifier: Development Status :: 4 - Beta
Classifier: Intended Audience :: Developers
Classifier: Intended Audience :: Science/Research
Classifier: License :: OSI Approved :: MIT License
Classifier: Programming Language :: Python :: 3
Classifier: Programming Language :: Python :: 3.9
Classifier: Programming Language :: Python :: 3.10
Classifier: Programming Language :: Python :: 3.11
Classifier: Programming Language :: Python :: 3.12
Classifier: Programming Language :: Python :: 3 :: Only
Classifier: Topic :: Scientific/Engineering :: Chemistry
Classifier: Topic :: Scientific/Engineering :: Artificial Intelligence
Classifier: Topic :: Scientific/Engineering :: Bio-Informatics
Classifier: Topic :: Scientific/Engineering :: Physics
Requires-Python: >=3.9
License-File: LICENSE.md
Requires-Dist: joblib >=1.4.2
Requires-Dist: numpy >=1.26.4
Requires-Dist: rdkit >=2023.9.6
Requires-Dist: scikit-learn >=1.5.0
Requires-Dist: scikit-learn-extra >=0.3.0
Requires-Dist: scipy >=1.13.1
Requires-Dist: typing-extensions >=4.12.1
Requires-Dist: umap-learn >=0.5.6
Provides-Extra: dev
Requires-Dist: coverage >=7.5.3 ; extra == 'dev'
Requires-Dist: ipykernel >=6.29.4 ; extra == 'dev'
Requires-Dist: matplotlib >=3.9.0 ; extra == 'dev'
Requires-Dist: myst-parser >=3.0.1 ; extra == 'dev'
Requires-Dist: pre-commit >=3.7.1 ; extra == 'dev'
Requires-Dist: pyright >=1.1.365 ; extra == 'dev'
Requires-Dist: pytest >=8.2.1 ; extra == 'dev'
Requires-Dist: rdkit-stubs >=0.7 ; extra == 'dev'
Requires-Dist: sphinx >=7.3.7 ; extra == 'dev'
Requires-Dist: sphinxcontrib-serializinghtml >=1.1.10 ; extra == 'dev'
Requires-Dist: sphinx-rtd-theme >=2.0.0 ; extra == 'dev'
Requires-Dist: twine >=5.1.0 ; extra == 'dev'
